Metadata-Version: 2.4
Name: jimeng-mcp-volcengine
Version: 1.0.2
Summary: 即梦AI MCP服务器 - 火山引擎官方API直连版本
Home-page: https://github.com/Ceeon/jimeng-mcp-volcengine
Author: Ceeon
Author-email: your-email@example.com
Project-URL: Bug Reports, https://github.com/Ceeon/jimeng-mcp-volcengine/issues
Project-URL: Source, https://github.com/Ceeon/jimeng-mcp-volcengine
Keywords: mcp jimeng ai image-generation volcengine doubao seedream ark
Classifier: Development Status :: 5 - Production/Stable
Classifier: Intended Audience :: Developers
Classifier: Topic :: Software Development :: Libraries :: Python Modules
Classifier: Topic :: Multimedia :: Graphics
Classifier: License :: OSI Approved :: MIT License
Classifier: Programming Language :: Python :: 3
Classifier: Programming Language :: Python :: 3.8
Classifier: Programming Language :: Python :: 3.9
Classifier: Programming Language :: Python :: 3.10
Classifier: Programming Language :: Python :: 3.11
Classifier: Operating System :: OS Independent
Requires-Python: >=3.8
License-File: LICENSE
Requires-Dist: fastmcp>=0.1.0
Requires-Dist: httpx[socks]>=0.24.0
Requires-Dist: Pillow>=10.0.0
Dynamic: author
Dynamic: author-email
Dynamic: classifier
Dynamic: description
Dynamic: description-content-type
Dynamic: home-page
Dynamic: keywords
Dynamic: license-file
Dynamic: project-url
Dynamic: requires-dist
Dynamic: requires-python
Dynamic: summary
